haikunator.py
pyhaikunator-0.0.3.dist-info/DESCRIPTION.rst
pyhaikunator-0.0.3.dist-info/metadata.json
pyhaikunator-0.0.3.dist-info/METADATA
pyhaikunator-0.0.3.dist-info/RECORD
pyhaikunator-0.0.3.dist-info/WHEEL
pyhaikunator-0.0.3.dist-info/top_level.txt
