Metadata-Version: 2.0
Name: pyhaikunator
Version: 0.0.3
Summary: Heroku like random name generator
Home-page: https://github.com/ferhatelmas.pyhaikunator
Author: Ferhat Elmas
Author-email: elmas.ferhat@gmail.com
License: MIT
Platform: UNKNOWN
Classifier: Programming Language :: Python :: 2
Classifier: Programming Language :: Python :: 3
Classifier: Intended Audience :: Developers
Classifier: License :: OSI Approved :: MIT License
Classifier: Topic :: Software Development :: Libraries
Classifier: Topic :: Utilities
